{
  "format_version": "1.8.0",
  "minecraft:spawn_rules": {
    "description": {
      "identifier": "thump989:brine",
      "population_control": "monster"
    },
    "conditions": [
      {
        "minecraft:spawns_on_surface": {},
        "minecraft:spawns_underwater": {},
        "minecraft:weight": {
          "default": 10
        },
        "minecraft:density_limit": {
          "surface": 3
        },
        "minecraft:brightness_filter": {
          "min": 0,
          "max": 7,
          "adjust_for_weather": true
        },
        "minecraft:biome_filter": {
          "test": "has_biome_tag",
          "operator": "==",
          "value": "deep"
        },
        "minecraft:world_age_filter": {
          "min": 6000
        }
      }
    ]
  }
}
